aiconsole/__init__.py
aiconsole/acceptance_tests.py
aiconsole/api/__init__.py
aiconsole/api/endpoints/__init__.py
aiconsole/api/endpoints/assets/__init__.py
aiconsole/api/endpoints/assets/asset.py
aiconsole/api/endpoints/assets/chat_options.py
aiconsole/api/endpoints/assets/index.py
aiconsole/api/endpoints/assets/preview.py
aiconsole/api/endpoints/check_key.py
aiconsole/api/endpoints/commands_history.py
aiconsole/api/endpoints/genui/__init__.py
aiconsole/api/endpoints/genui/index.py
aiconsole/api/endpoints/image.py
aiconsole/api/endpoints/ping.py
aiconsole/api/endpoints/profile.py
aiconsole/api/endpoints/projects/__init__.py
aiconsole/api/endpoints/projects/choose.py
aiconsole/api/endpoints/projects/close.py
aiconsole/api/endpoints/projects/recent.py
aiconsole/api/endpoints/projects/registry.py
aiconsole/api/endpoints/projects/services.py
aiconsole/api/endpoints/projects/tests/__init__.py
aiconsole/api/endpoints/projects/tests/test_project_directory.py
aiconsole/api/endpoints/registry.py
aiconsole/api/endpoints/services.py
aiconsole/api/endpoints/settings.py
aiconsole/api/endpoints/ws.py
aiconsole/api/routers.py
aiconsole/api/websockets/__init__.py
aiconsole/api/websockets/base_server_message.py
aiconsole/api/websockets/client_messages.py
aiconsole/api/websockets/connection_manager.py
aiconsole/api/websockets/do_process_chat.py
aiconsole/api/websockets/handle_incoming_message.py
aiconsole/api/websockets/render_materials.py
aiconsole/api/websockets/server_messages.py
aiconsole/app.py
aiconsole/consts.py
aiconsole/core/adapters/__init__.py
aiconsole/core/adapters/material.py
aiconsole/core/assets/__init__.py
aiconsole/core/assets/agents/__init__.py
aiconsole/core/assets/agents/agent.py
aiconsole/core/assets/assets.py
aiconsole/core/assets/fs/__init__.py
aiconsole/core/assets/fs/delete_asset_from_fs.py
aiconsole/core/assets/fs/exceptions.py
aiconsole/core/assets/fs/load_asset_from_fs.py
aiconsole/core/assets/fs/move_asset_in_fs.py
aiconsole-0.2.13.dist-info/METADATA
aiconsole-0.2.13.dist-info/WHEEL
aiconsole-0.2.13.dist-info/entry_points.txt
aiconsole-0.2.13.dist-info/RECORD
